cypy_supersearch/__init__.py
cypy_supersearch/db.py
cypy_supersearch/gui.py
cypy_supersearch/indexer.py
cypy_supersearch/main.py
cypy_supersearch-2026.1.4.1.dist-info/LICENSE
cypy_supersearch-2026.1.4.1.dist-info/METADATA
cypy_supersearch-2026.1.4.1.dist-info/WHEEL
cypy_supersearch-2026.1.4.1.dist-info/entry_points.txt
cypy_supersearch-2026.1.4.1.dist-info/top_level.txt
cypy_supersearch-2026.1.4.1.dist-info/RECORD
